gladi/__init__.py
gladi-1.0.0.dist-info/licenses/LICENSE
gladi-1.0.0.dist-info/WHEEL
gladi-1.0.0.dist-info/METADATA
gladi-1.0.0.dist-info/RECORD
