Metadata-Version: 2.4
Name: gladi
Version: 1.0.0
Summary: A simple dependency injection library for Python
Keywords: dependency,injection,di
Author: cheeze2000
Author-email: cheeze2000 <me@cheeze2000.net>
License-Expression: Apache-2.0
License-File: LICENSE
Requires-Python: >=3.12
Project-URL: Repository, https://github.com/cheeze2000/gladi.git
